api_bouncer/__init__.py
api_bouncer/admin.py
api_bouncer/apps.py
api_bouncer/models.py
api_bouncer/schemas.py
api_bouncer/serializers.py
api_bouncer/urls.py
api_bouncer/validators.py
api_bouncer/views.py
api_bouncer/middleware/__init__.py
api_bouncer/middleware/acl.py
api_bouncer/middleware/bouncer.py
api_bouncer/middleware/ip_restriction.py
api_bouncer/middleware/key_auth.py
api_bouncer/middleware/request_termination.py
api_bouncer/migrations/0001_initial.py
api_bouncer/migrations/0002_consumer_acls.py
api_bouncer/migrations/__init__.py
django_api_bouncer-0.3.1.dist-info/DESCRIPTION.rst
django_api_bouncer-0.3.1.dist-info/METADATA
django_api_bouncer-0.3.1.dist-info/RECORD
django_api_bouncer-0.3.1.dist-info/WHEEL
django_api_bouncer-0.3.1.dist-info/metadata.json
django_api_bouncer-0.3.1.dist-info/top_level.txt
