Metadata-Version: 2.0
Name: django-api-bouncer
Version: 0.3.1
Summary: A simple API Gateway app for Django
Home-page: https://github.com/menecio/django-api-bouncer
Author: Aristobulo Meneses
Author-email: aristobulo@menecio.me
License: UNKNOWN
Download-URL: https://github.com/menecio/django-api-bouncer/tarball/master
Keywords: django,rest,api,gateway
Platform: UNKNOWN
Classifier: Environment :: Web Environment
Classifier: Framework :: Django
Classifier: Framework :: Django :: 1.11
Classifier: Intended Audience :: Developers
Classifier: License :: OSI Approved :: Apache Software License
Classifier: Operating System :: OS Independent
Classifier: Programming Language :: Python
Classifier: Programming Language :: Python :: 3
Classifier: Programming Language :: Python :: 3.5
Classifier: Programming Language :: Python :: 3.6
Classifier: Topic :: Internet :: WWW/HTTP
Classifier: Topic :: Internet :: WWW/HTTP :: Dynamic Content
Requires-Dist: django (>=1.10)
Requires-Dist: jsonschema (>=2.6.0)
Requires-Dist: requests (>=2.18.1)
Requires-Dist: psycopg2 (>=2.7.1)
Requires-Dist: djangorestframework (>=3.6.3)
